dagster_openai/__init__.py
dagster_openai/py.typed
dagster_openai/resources.py
dagster_openai/version.py
dagster_openai-0.28.13.dist-info/licenses/LICENSE
dagster_openai-0.28.13.dist-info/METADATA
dagster_openai-0.28.13.dist-info/WHEEL
dagster_openai-0.28.13.dist-info/top_level.txt
dagster_openai-0.28.13.dist-info/RECORD
