Metadata-Version: 2.4
Name: dagster-openai
Version: 0.28.13
Summary: An OpenAI client resource for interacting with OpenAI API.
Home-page: https://github.com/dagster-io/dagster/tree/master/python_modules/libraries/dagster-openai
Author: Dagster Labs
Author-email: hello@dagsterlabs.com
License: Apache-2.0
Classifier: Programming Language :: Python :: 3.10
Classifier: Programming Language :: Python :: 3.11
Classifier: License :: OSI Approved :: Apache Software License
Classifier: Operating System :: OS Independent
License-File: LICENSE
Requires-Dist: dagster==1.12.13
Requires-Dist: openai
Dynamic: author
Dynamic: author-email
Dynamic: classifier
Dynamic: home-page
Dynamic: license
Dynamic: license-file
Dynamic: requires-dist
Dynamic: summary
